gramo_client_ager/__init__.py
gramo_client_ager/client.py
gramo_client_ager/exceptions.py
gramo_client_ager/models.py
gramo_client_ager-0.1.0.dist-info/METADATA
gramo_client_ager-0.1.0.dist-info/WHEEL
gramo_client_ager-0.1.0.dist-info/RECORD
