Metadata-Version: 2.4
Name: gramo_client_ager
Version: 0.1.0
Summary: A Python client for the Gramosynth API
Project-URL: Homepage, https://github.com/rightsify/gramo_client
Project-URL: Bug Tracker, https://github.com/rightsify/gramo_client/issues
Author-email: Ager Austen <ager@rightsify.com>
License-Expression: MIT
Keywords: api,client,gramosynth
Classifier: Development Status :: 3 - Alpha
Classifier: Intended Audience :: Developers
Classifier: License :: OSI Approved :: MIT License
Classifier: Programming Language :: Python :: 3
Classifier: Programming Language :: Python :: 3.7
Classifier: Programming Language :: Python :: 3.8
Classifier: Programming Language :: Python :: 3.9
Classifier: Programming Language :: Python :: 3.10
Requires-Python: >=3.7
Requires-Dist: dataclasses; python_version < '3.7'
Requires-Dist: httpx>=0.24.0
Provides-Extra: test
Requires-Dist: pytest-asyncio>=0.20.0; extra == 'test'
Requires-Dist: pytest-cov>=4.0.0; extra == 'test'
Requires-Dist: pytest>=7.0; extra == 'test'
